{"relativePath":"/posts/2003/12/17/wmd-treasure-hunt","comments":"","pubDate":"2003-12-17T10:24:00-05:00","title":"WMD treasure hunt","subtitle":"","intro":"","categories":["gamez"],"body":"&lt;!-- id=292--&gt;&lt;!-- isMature=0 --&gt;&lt;A HREF=&quot;http://www.findthoseweapons.com/index.htm&quot;&gt;win money, gold, and oil!!!&lt;/A&gt; (it&#x27;s for real!)","enclosures":[],"source":{"url":"","title":""},"changefreq":"never","priority":"0.1","bodyArticleHtml":"<hgroup><h3><time datetime=\"2003-12-17T15:24:00.000Z\" pubdate=\"pubdate\">2003-12-17</time></h3><h1><a href=\"http://travis.servebeer.com/posts/2003/12/17/wmd-treasure-hunt\">WMD treasure hunt</a></h1><h2></h2></hgroup><!-- id=292--><!-- isMature=0 --><A HREF="http:"bodyNavItems":[{"pageRel":"prev","href":"/posts/2003/12/21/etc","text":"..."},{"pageRel":"prev","href":"/posts/2003/12/17/it-s-the-holiday-season","text":"it&#x27;s the holiday season..."},{"pageRel":"self","href":"/posts/2003/12/17/wmd-treasure-hunt","text":"WMD treasure hunt"},{"pageRel":"next","href":"/posts/2003/12/16/beer-cds-remix","text":"beer+cds=remix"},{"href":"/posts/2003/12/15/ugh","text":"ugh"}]}