{"relativePath":"/posts/2005/06/17/the-american-taliban","comments":"[object Object],[object Object]","pubDate":"2005-06-17T08:00:00-04:00","title":"The American Taliban","subtitle":"","intro":"","categories":["politix"],"body":"&lt;p&gt;One of the &lt;a href=&quot;http://www.reandev.com/taliban/&quot;&gt;scariest things about these quotes&lt;/a&gt; is the power and positions that the people who said them have. The sad thing is that there are probably many Americans who agree with them.&lt;/p&gt;","enclosures":[],"source":{"url":"","title":""},"changefreq":"never","priority":"0.1","bodyArticleHtml":"<hgroup><h3><time datetime=\"2005-06-17T12:00:00.000Z\" pubdate=\"pubdate\">2005-06-17</time></h3><h1><a href=\"http://dieseltravis.github.io/posts/2005/06/17/the-american-taliban\">The American Taliban</a></h1><h2></h2></hgroup><p>One of the <a href="http:"bodyNavItems":[{"pageRel":"prev","href":"/posts/2005/07/08/feedburner","text":"Feedburner"},{"pageRel":"prev","href":"/posts/2005/07/08/100-419ers","text":"100+ 419ers"},{"pageRel":"self","href":"/posts/2005/06/17/the-american-taliban","text":"The American Taliban"},{"pageRel":"next","href":"/posts/2005/06/16/everything-you-wanted-to-know-about-rochester","text":"Everything you wanted to know about Rochester"},{"href":"/posts/2005/06/15/triumph-jacko","text":"Triumph Jacko"}]}