{"relativePath":"/posts/2004/06/08/allofmp3-com","comments":"","pubDate":"2004-06-08T06:25:00-04:00","title":"allofmp3.com","subtitle":"","intro":"","categories":["music","tech"],"body":"&lt;a title=&quot;Ern&quot; href=&quot;http://ern.hopto.org/blog&quot; &gt;Ern&lt;/a&gt; found a &lt;a href=&quot;http://ern.hopto.org/blog/archive/2004/06/08/251.aspx&quot;&gt;sweet music site&lt;/a&gt; - the formats supported are ridiculous.  The price is a $0.01/MB, so for $25 you can buy 2.5&lt;strong&gt;GB&lt;/strong&gt; of music, AND it&#x27;ll be in the format of your choice.  w00t!&lt;br/&gt;[EDIT] - bad math :-P","enclosures":[],"source":{"url":"","title":""},"changefreq":"never","priority":"0.1","bodyArticleHtml":"<hgroup><h3><time datetime=\"2004-06-08T10:25:00.000Z\" pubdate=\"pubdate\">2004-06-08</time></h3><h1><a href=\"http://dieseltravis.github.io/posts/2004/06/08/allofmp3-com\">allofmp3.com</a></h1><h2></h2></hgroup><a title="Ern" href="http:[EDIT]-badmath:-P",	"bodyNavItems": [								{								"href": "/posts/2004/06/09/new-ford-focus-concept",				"text": "NewFordFocusConcept"			}					, 			{									"pageRel": "prev",								"href": "/posts/2004/06/08/tornado-safety",				"text": "TornadoSafety"			}					, 			{									"pageRel": "self",								"href": "/posts/2004/06/08/allofmp3-com",				"text": "allofmp3.com"			}					, 			{									"pageRel": "next",								"href": "/posts/2004/06/07/zombo-fark",				"text": "ZomboFark"			}					, 			{								"href": "/posts/2004/06/03/talkin-bout-movin",				"text": "Talkin&#x27;&#x27;boutmovin&#x27;"			}			]}