{"relativePath":"/posts/2003/11/04/etc","comments":"","pubDate":"2003-11-04T04:36:00-05:00","title":"...","subtitle":"","intro":"","categories":["tech","quote"],"body":"&lt;!-- id=273--&gt;&lt;!-- isMature=0 --&gt;&lt;A HREF=&quot;http://www.kptv.com/Global/SearchResults.asp?qu=tomacco&quot;&gt;&quot;tastes like grandma&quot;&lt;/A&gt;","enclosures":[],"source":{"url":"","title":""},"changefreq":"never","priority":"0.1","bodyArticleHtml":"<hgroup><h3><time datetime=\"2003-11-04T09:36:00.000Z\" pubdate=\"pubdate\">2003-11-04</time></h3><h1><a href=\"http://dieseltravis.github.io/posts/2003/11/04/etc\">...</a></h1><h2></h2></hgroup><!-- id=273--><!-- isMature=0 --><A HREF="http:"bodyNavItems":[{"pageRel":"prev","href":"/posts/2003/11/10/mushroom","text":"mushroom?"},{"pageRel":"prev","href":"/posts/2003/11/09/etc","text":"..."},{"pageRel":"self","href":"/posts/2003/11/04/etc","text":"..."},{"pageRel":"next","href":"/posts/2003/11/03/do-you-have-any-dreams","text":"do you have any dreams?"},{"href":"/posts/2003/11/03/20-questions","text":"20 questions"}]}