{"relativePath":"/posts/2004/06/30/setiboinc","comments":"[object Object]","pubDate":"2004-06-30T07:26:00-04:00","title":"SetiBOINC","subtitle":"","intro":"","categories":["tech"],"body":"&lt;a href=&quot;http://setiathome.ssl.berkeley.edu/&quot;&gt;Seti@Home&lt;/a&gt; is &lt;a href=&quot;http://setiboinc.ssl.berkeley.edu/sah/transition.php&quot;&gt;transitioning&lt;/a&gt; over to the all new &lt;a href=&quot;http://setiboinc.ssl.berkeley.edu/sah/&quot;&gt;BOINC system&lt;/a&gt;.  There are &lt;a href=&quot;http://setiboinc.ssl.berkeley.edu/sah/sah_participate.php&quot;&gt;new clients&lt;/a&gt; which are allegedly better than the &quot;Classic&quot; seti@home clients.  One advantage they have is that they are self-queuing so there&#x27;s no need to run a &lt;a href=&quot;http://travis.servebeer.com:5517/&quot;&gt;proxy server&lt;/a&gt;.  Some of the new/updated features the BOINC system has include: &lt;a href=&quot;http://setiboinc.ssl.berkeley.edu/sah/view_profile.php?userid=60447&quot;&gt;user profile&lt;/a&gt;, &lt;a href=&quot;http://setiboinc.ssl.berkeley.edu/sah/team_display.php?teamid=40081&quot;&gt;teams&lt;/a&gt; (migrated from &quot;Classic&quot;), &lt;a href=&quot;http://setiboinc.ssl.berkeley.edu/sah/pending.php?userid=60447&quot;&gt;pending credit&lt;/a&gt;, &lt;a href=&quot;http://setiboinc.ssl.berkeley.edu/sah/hosts_user.php?userid=60447&quot;&gt;stats for your different computers&lt;/a&gt;, and  of course &lt;a href=&quot;http://setiboinc.ssl.berkeley.edu/sah/results.php?userid=60447&quot;&gt;results&lt;/a&gt;.  Overall &lt;a href=&quot;http://boinc.berkeley.edu/&quot;&gt;BOINC&lt;/a&gt; sounds pretty cool.  Although it&#x27;s been running for about an hour now and it hasn&#x27;t done any work, probably because the Berkeley servers are getting hammered with new data unit requests. (If someone happens to come across an x86_64 client let me know!)","enclosures":[],"source":{"url":"","title":""},"changefreq":"never","priority":"0.1","bodyArticleHtml":"<hgroup><h3><time datetime=\"2004-06-30T11:26:00.000Z\" pubdate=\"pubdate\">2004-06-30</time></h3><h1><a href=\"http://dieseltravis.github.io/posts/2004/06/30/setiboinc\">SetiBOINC</a></h1><h2></h2></hgroup><a href="http:"bodyNavItems":[{"pageRel":"prev","href":"/posts/2004/07/01/beta-imagezoomer-v0-2-test","text":"beta ImageZoomer v0.2 (test!)"},{"pageRel":"prev","href":"/posts/2004/06/30/alpha-imagezoomer-v0-2-help","text":"alpha ImageZoomer v0.2 (help!)"},{"pageRel":"self","href":"/posts/2004/06/30/setiboinc","text":"SetiBOINC"},{"pageRel":"next","href":"/posts/2004/06/29/it-s-the-summer-of-express-on-channel-9","text":"It&#x27;s the summer of Express on Channel 9"},{"href":"/posts/2004/06/29/firefox-0-9-1","text":"Firefox 0.9.1"}]}