{"relativePath":"/posts/2002/09/04/techno-puppet","comments":"[object Object],[object Object],[object Object],[object Object],[object Object]","pubDate":"2002-09-04T19:09:00-04:00","title":"techno puppet","subtitle":"","intro":"","categories":[],"body":"&lt;!-- id=73--&gt;&lt;!-- isMature=0 --&gt;check this &lt;a href=&quot;http://www.albinoblacksheep.com/flash/technopuppet.html&quot;&gt;mutha out&lt;/a&gt;","enclosures":[],"source":{"url":"","title":""},"changefreq":"never","priority":"0.1","bodyArticleHtml":"<hgroup><h3><time datetime=\"2002-09-04T23:09:00.000Z\" pubdate=\"pubdate\">2002-09-04</time></h3><h1><a href=\"http://dieseltravis.github.io/posts/2002/09/04/techno-puppet\">techno puppet</a></h1><h2></h2></hgroup><!-- id=73--><!-- isMature=0 -->check this <a href="http:"bodyNavItems":[{"href":"/posts/2002/09/07/hehe","text":"hehe"},{"pageRel":"prev","href":"/posts/2002/09/05/like-whoa","text":"like whoa"},{"pageRel":"self","href":"/posts/2002/09/04/techno-puppet","text":"techno puppet"},{"pageRel":"next","href":"/posts/2002/08/31/me","text":"me"},{"href":"/posts/2002/08/23/hmm","text":"hmm"}]}