{"relativePath":"/posts/2004/04/06/playing-mario-bros","comments":"[object Object],[object Object]","pubDate":"2004-04-06T10:28:00-04:00","title":"Playing Mario Bros","subtitle":"","intro":"","categories":["gamez","KS","music","tech"],"body":"Now &lt;a href=&quot;http://momsbox.com/redir.php?key=0000012748&quot;&gt;this dude knows how to &lt;em&gt;play&lt;/em&gt; Super Mario Bros&lt;/a&gt;[wmv].","enclosures":[],"source":{"url":"","title":""},"changefreq":"never","priority":"0.1","bodyArticleHtml":"<hgroup><h3><time datetime=\"2004-04-06T14:28:00.000Z\" pubdate=\"pubdate\">2004-04-06</time></h3><h1><a href=\"http://travis.servebeer.com/posts/2004/04/06/playing-mario-bros\">Playing Mario Bros</a></h1><h2></h2></hgroup>Now <a href="http:"bodyNavItems":[{"pageRel":"prev","href":"/posts/2004/04/07/absoludicrous-","text":"Absoludicrous!"},{"pageRel":"prev","href":"/posts/2004/04/06/homo-sapien-1-0","text":"Homo Sapien 1.0"},{"pageRel":"self","href":"/posts/2004/04/06/playing-mario-bros","text":"Playing Mario Bros"},{"pageRel":"next","href":"/posts/2004/04/06/-made-in-the-usa-my-ass","text":"&quot;Made in the USA&quot; my ass"},{"href":"/posts/2004/04/06/npr-s-car-talk-lets-me-down","text":"NPR&#x27;s Car Talk lets me down"}]}