{"relativePath":"/posts/2004/12/15/to-gmail-spam-filter-merry-christmas-from-worm-zafi-d","comments":"[object Object],[object Object],[object Object],[object Object]","pubDate":"2004-12-15T10:49:00-05:00","title":"To: Gmail Spam filter, Merry Christmas! From: Worm.Zafi.D","subtitle":"","intro":"","categories":["local","tech","wtf"],"body":"&lt;p&gt;Thanks to whoever the a-hole is that got the Merry Christmas worm that spoofed my gmail address as the sender. I really enjoyed 12:35pm to 2:43pm when I received 560 bounce messages.  Look at the screenshot below, and check out the times at the right and the number of threaded messages in parentheses:&lt;/p&gt;&lt;p&gt;&lt;a href=&quot;http://travis.servebeer.com/blog.net/images/28/o_Merry_Christmas_gmail.png&quot; title=&quot;look at my gmail&#x27;s spam folder, ridiculous&quot;&gt;&lt;img src=&quot;http://travis.servebeer.com/blog.net/images/28/t_Merry_Christmas_gmail.png&quot; alt=&quot;thumb of my gmail spam folder&quot; /&gt;&lt;/a&gt;&lt;/p&gt;&lt;p&gt;&lt;a href=&quot;http://travis.servebeer.com/MSNvsGoogle.html?sourceid=Mozilla-search&amp;amp;q=%22Merry+Christmas%21%22+Zafi&quot; title=&quot;more on Zafi&quot;&gt;more on Zafi&lt;/a&gt;&lt;/p&gt;","enclosures":[],"source":{"url":"","title":""},"changefreq":"never","priority":"0.1","bodyArticleHtml":"<hgroup><h3><time datetime=\"2004-12-15T15:49:00.000Z\" pubdate=\"pubdate\">2004-12-15</time></h3><h1><a href=\"http://travis.servebeer.com/posts/2004/12/15/to-gmail-spam-filter-merry-christmas-from-worm-zafi-d\">To: Gmail Spam filter, Merry Christmas! From: Worm.Zafi.D</a></h1><h2></h2></hgroup><p>Thanks to whoever the a-hole is that got the Merry Christmas worm that spoofed my gmail address as the sender. I really enjoyed 12:35pm to 2:43pm when I received 560 bounce messages.  Look at the screenshot below, and check out the times at the right and the number of threaded messages in parentheses:</p><p><a href="http:</p><p><ahref="http://travis.servebeer.com/MSNvsGoogle.html?sourceid=Mozilla-search&amp;q=%22Merry+Christmas%21%22+Zafi"title="more on Zafi">moreonZafi</a></p>",	"bodyNavItems": [								{									"pageRel": "prev",								"href": "/posts/2004/12/30/asia-earthquake-and-tsunami-fund",				"text": "AsiaEarthquakeandTsunamiFund"			}					, 			{									"pageRel": "prev",								"href": "/posts/2004/12/22/to-gmail-spam-filter-merry-christmas-from-worm-zafi-d-part-2",				"text": "To:GmailSpamfilter,MerryChristmas!From:Worm.Zafi.DPart2"			}					, 			{									"pageRel": "self",								"href": "/posts/2004/12/15/to-gmail-spam-filter-merry-christmas-from-worm-zafi-d",				"text": "To:GmailSpamfilter,MerryChristmas!From:Worm.Zafi.D"			}					, 			{									"pageRel": "next",								"href": "/posts/2004/12/14/hanukkah-beer-he-brew-the-chosen-beer",				"text": "HanukkahBeer:He&#x27;Brew,Thechosenbeer"			}					, 			{								"href": "/posts/2004/12/09/i-think-this-is-the-mother-of-all-419ers",				"text": "Ithinkthisisthemotherofall419ers"			}			]}